PineUtils/Array2D.py
PineUtils/Files.py
PineUtils/Input.py
PineUtils/Logger.py
PineUtils/__init__.py
PineUtils/main.py
PineUtils/test.py
PineUtils-0.1.0.dist-info/LICENSE
PineUtils-0.1.0.dist-info/License.txt
PineUtils-0.1.0.dist-info/METADATA
PineUtils-0.1.0.dist-info/WHEEL
PineUtils-0.1.0.dist-info/top_level.txt
PineUtils-0.1.0.dist-info/RECORD
