Metadata-Version: 2.1
Name: PineUtils
Version: 0.1.0
Home-page: https://github.com/plaraje/PineUtils
Author: Plaraje (DMAM2)
Author-email: plaraje@proton.me
License: GNU AFFERO GENERAL PUBLIC LICENSE
Classifier: Programming Language :: Python :: 3
Classifier: Operating System :: OS Independent
License-File: LICENSE
License-File: License.txt
Requires-Dist: Chromify
